{
  "posts": [
    { "id": 1, "title": "Post 1" },
    { "id": 2, "title": "Post 2" },
    { "id": 3, "title": "Post 3" }
  ],
  "comments": [
    { "id": 1, "body": "some comment", "postId": 1 },
    { "id": 2, "body": "some comment", "postId": 1 }
  ],
  "singleProduct": {
    "id": "1001",
    "hits":"45",
    "title": "lipstick",
    "name": "Golden",
    "price": 234.00,
    "desc": "sddfhjkiuo werghuio qawe sddfhjkiuo werghuio qawe sddfhjkiuo werghuio qawe",
    "stars": "1 < NUMBER < 5",
    "image": "IMAGEurl",
    "categoryid": "categoryId1",
    "categoryname": "lips",
    "new": "true",
    "imgUrl": "//media.gucci.com/style/White_South_0_160_235x235/1554389107/586168_9PLP7_9501_001_100_0000_Light-501-Constance-Vermillon-Rouge-Lvres-Satin-Lipstick.jpg",
    "imgUrl2": "//media.gucci.com/style/White_South_0_160_235x235/1554382805/586169_9PLP8_9525_001_100_0000_Light-25-Goldie-Red-Rouge-Lvres-Voile-Lipstick.jpg",
    "imgUrl3":"https://media.gucci.com/style/DarkGray_Center_0_0_800x800/1554382805/586169_9PLP8_9525_001_100_0000_Light-25-Goldie-Red-Rouge-Lvres-Voile-Lipstick.jpg",
    "weight":"0.2 Oz",
    "description":"For Europe, we offer Free Express shipping with all orders (except for those delivered with the Saturday delivery option). From the moment the order leaves our warehouse, we deliver in 1-2 business days (or 2-3 business days in UAE), if not differently specified in the product availability information. All orders are processed Monday through Saturday (Saturday only where the service is available and has been selected), excluding Sunday and holidays.Additional shipping information is available during the checkout process.",
    "benefits":"You must inform Gucci of your intention to return the merchandise within 14 days of the date of delivery either by (i) directly returning the merchandise to Gucci together with the original invoice duly filled-in; or (ii) sending to Gucci the form downloadable here or any other unequivocal statement and then returning to Gucci the merchandise with the original invoice duly filled-in within 14 days after the day on which you sent the form (or any other unequivocal statement) to Gucci. You can use the free return label provided with each shipment to return your purchase. Refunds will be issued in the same form as was utilized for payment."

  },
  "products":  [
    {
      "id": "1001",
      "hits":"234",
      "title": "lipstick",
      "name": "Golden",
      "price": 234.00,
      "desc": "sddfhjkiuo werghuio qawe sddfhjkiuo werghuio qawe sddfhjkiuo werghuio qawe",
      "stars": "1<NUMBER<5",
      "image": "IMAGEurl",
      "categoryid": "categoryId1",
      "categoryname":"lips",
      "new":"true",
      "imgUrl" : "http://media.gucci.com/style/DarkGray_South_0_160_316x316/1563810304/563041_99999_0099_001_100_0000_Light-Gucci-Flora-Emerald-Gardenia-100-ml-Eau-de-Toilette.jpg",
      "imgUrl1":"http://media.gucci.com/style/White_South_0_160_316x316/1563810304/563041_99999_0099_002_100_0000_Light.jpg"

    },
    {
      "id": "10012",
      "hits":"244",
      "title": "balm",
      "name": "Golden",
      "price": 444.00,
      "desc": "sddfhjkiuo werghuio qawe sddfhjkiuo werghuio qawe sddfhjkiuo werghuio qawe",
      "stars": "1<NUMBER<5",
      "image": "IMAGEurl",
      "categoryid": "categoryId1",
      "categoryname":"lips",
      "new":"true",
      "imgUrl":"http://media.gucci.com/style/DarkGray_South_0_160_316x316/1545327903/399201_99999_0099_001_100_0000_Light-Gucci-Flora-Gorgeous-Gardenia-100ml-Eau-de-Toilette.jpg",
      "imgUrl1":"http://media.gucci.com/style/White_South_0_160_316x316/1545327904/399201_99999_0099_002_100_0000_Light.jpg"
    },
    {
      "id": "1002",
      "hits":"345",
      "title": "pancake",
      "name": "Bronze",
      "price": 234.00,
      "desc": "sddfhjkiuo werghuio qawe sddfhjkiuo werghuio qawe sddfhjkiuo werghuio qawe",
      "stars": "1<NUMBER<5",
      "image": "IMAGEurl",
      "categoryid": "categoryId2",
      "categoryname":"face",
      "new":"false",
      "imgUrl":"http://media.gucci.com/style/DarkGray_South_0_160_316x316/1531751407/401268_99999_0099_001_100_0000_Light-Gucci-Bamboo-50ml-Eau-de-Parfum.jpg",
      "imgUrl1":"http://media.gucci.com/style/White_South_0_160_316x316/1531751407/401268_99999_0099_002_100_0000_Light.jpg"
    },
    {
      "id": "10021",
      "hits":"902",
      "title": "masacara",
      "name": "Bronze",
      "price": 234.00,
      "desc": "sddfhjkiuo werghuio qawe sddfhjkiuo werghuio qawe sddfhjkiuo werghuio qawe",
      "stars": "1<NUMBER<5",
      "image": "IMAGEurl",
      "categoryid": "categoryId2",
      "categoryname":"face",
      "new":"false",
      "imgUrl":"http://media.gucci.com/style/DarkGray_South_0_160_316x316/1554385508/586168_9PLP7_9502_001_100_0000_Light-502-Eadie-Scarlet-Rouge-Lvres-Satin-Lippenstift.jpg",
      "imgUrl1":"http://media.gucci.com/style/White_South_0_160_316x316/1554385508/586168_9PLP7_9502_002_100_0000_Light.jpg"
    },
    {
      "id": "1003",
      "hits":"4567",
      "title": "Brush",
      "name": "silver",
      "price": 555.00,
      "desc": "sddfhjkiuo werghuio qawe sddfhjkiuo werghuio qawe sddfhjkiuo werghuio qawe",
      "stars": "1<NUMBER<5",
      "image": "IMAGEurl",
      "categoryid": "categoryId3",
      "categoryname":"brush",
      "new":"false",
      "imgUrl":"http://media.gucci.com/style/DarkGray_South_0_160_316x316/1554383706/586169_9PLP8_9301_001_100_0000_Light-301-Mae-Coral-Rouge-Lvres-Voile-Lippenstift.jpg",
      "imgUrl1":"http://media.gucci.com/style/White_South_0_160_316x316/1554383706/586169_9PLP8_9301_002_100_0000_Light.jpg"
    },
    {
      "id": "10031",
      "hits":"456",
      "title": "eyepowder",
      "name": "silver",
      "price": 888.00,
      "desc": "sddfhjkiuo werghuio qawe sddfhjkiuo werghuio qawe sddfhjkiuo werghuio qawe",
      "stars": "1<NUMBER<5",
      "image": "IMAGEurl",
      "categoryid": "categoryId3",
      "categoryname":"brush",
      "new":"false",
      "imgUrl":"http://media.gucci.com/style/DarkGray_South_0_160_316x316/1554987603/586170_9PLP9_9001_001_100_0000_Light-1-Joslyn-Clair-Baume-Lvres-Lip-Balm.jpg",
      "imgUrl1":"http://media.gucci.com/style/White_South_0_160_316x316/1554987603/586170_9PLP9_9001_002_100_0000_Light-1-Joslyn-Clair-Baume-Lvres-Lip-Balm.jpg"
    },
    {
      "id": "1004",
      "hits":"564",
      "title": "nail",
      "name": "golden",
      "price": 555.00,
      "desc": "sddfhjkiuo werghuio qawe sddfhjkiuo werghuio qawe sddfhjkiuo werghuio qawe",
      "stars": "1<NUMBER<5",
      "image": "IMAGEurl",
      "categoryid": "categoryId4",
      "categoryname":"nail",
      "new":"false",
      "imgUrl": "",
      "imgUrl1": ""
    },
    {
      "id": "10041",
      "hits":"234",
      "title": "powder",
      "name": "golden",
      "price": 545.00,
      "desc": "sddfhjkiuo werghuio qawe sddfhjkiuo werghuio qawe sddfhjkiuo werghuio qawe",
      "stars": "1<NUMBER<5",
      "image": "IMAGEurl",
      "categoryid": "categoryId4",
      "categoryname":"nail",
      "new":"false",
      "imgUrl": "",
      "imgUrl1": ""
    }
  ]
}
